{
    "name": "n pad thai",
    "Food_Item_UUID": "01b98321-70ee-4cea-9a21-a10eec98d33f",
    "User_UUID": "c9867a74-4d90-413a-83de-80964ce64709",
    "Description": "rice stick noodle with egg batter bean sprout and chives",
    "Flavor_Profile": {
        "Taste": [],
        "Aroma": [],
        "Texture": [],
        "Visual_Color": [],
        "Spice_level": []
    },
    "Societal_Properties": {
        "Dietary_restrictions": [],
        "Nutrition": [],
        "Country_Origin": [],
        "Occasions": [],
        "Cooking_Method": [],
        "Course": []
    },
    "Food_History": {
        "Likes": [],
        "Comments": [],
        "Reviews": [],
        "Amt_bought": [],
        "Promoted": []
    }
}