{
    "name": "a chicken curry puff each ",
    "Food_Item_UUID": "308dc132-fb42-408b-bd36-9bd87776c6be",
    "User_UUID": "c9867a74-4d90-413a-83de-80964ce64709",
    "Description": "puff pastry folded with potato onion carrot and curry powder",
    "Flavor_Profile": {
        "Taste": [
            "Umami"
        ],
        "Aroma": [
            "Spicy"
        ],
        "Texture": [
            "Crunchy",
            "Soft"
        ],
        "Visual_Color": [
            "Brown"
        ],
        "Spice_level": []
    },
    "Societal_Properties": {
        "Dietary_restrictions": [],
        "Nutrition": [],
        "Country_Origin": [],
        "Occasions": [
            "Snack"
        ],
        "Cooking_Method": [
            "Fried"
        ],
        "Course": [
            "Appetizer"
        ]
    },
    "Food_History": {
        "Likes": [],
        "Comments": [],
        "Reviews": [],
        "Amt_bought": [],
        "Promoted": []
    }
}