{
    "name": "add enchilada",
    "Food_Item_UUID": "ad627b93-ef33-461c-9339-67d3450af4cb",
    "User_UUID": "8f90c2ea-b027-4a05-a5ea-969134c8652c",
    "Description": "No Description Provided",
    "Flavor_Profile": {
        "Taste": [],
        "Aroma": [],
        "Texture": [
            "Soft"
        ],
        "Visual_Color": [
            "Brown"
        ],
        "Spice_level": []
    },
    "Societal_Properties": {
        "Dietary_restrictions": [],
        "Nutrition": [],
        "Country_Origin": [],
        "Occasions": [],
        "Cooking_Method": [
            "Baked"
        ],
        "Course": [
            "Main Course"
        ]
    },
    "Food_History": {
        "Likes": [],
        "Comments": [],
        "Reviews": [],
        "Amt_bought": [],
        "Promoted": []
    }
}