{
    "name": "spicy rigatoni vodka",
    "Food_Item_UUID": "e13d19b2-c509-46f1-bf90-2f6cf8807f5b",
    "User_UUID": "43647973-fc56-4a74-9866-56edb9006d27",
    "Description": "italian sausage crispy pancetta shaved garlic torn basil grana padano",
    "Flavor_Profile": {
        "Taste": [
            "Umami",
            "Sour"
        ],
        "Aroma": [
            "Spicy",
            "Nutty"
        ],
        "Texture": [
            "Chewy"
        ],
        "Visual_Color": [
            "Brown",
            "White"
        ],
        "Spice_level": [
            "Hot"
        ]
    },
    "Societal_Properties": {
        "Dietary_restrictions": [],
        "Nutrition": [],
        "Country_Origin": [
            "Italy"
        ],
        "Occasions": [],
        "Cooking_Method": [],
        "Course": [
            "Main Course"
        ]
    },
    "Food_History": {
        "Likes": [],
        "Comments": [],
        "Reviews": [],
        "Amt_bought": [],
        "Promoted": []
    }
}