{
    "name": "cleto chiarli brut de noir sparkling rose",
    "Food_Item_UUID": "be74e008-128e-47c6-9124-986697cbbe9b",
    "User_UUID": "43647973-fc56-4a74-9866-56edb9006d27",
    "Description": " abv",
    "Flavor_Profile": {
        "Taste": [
            "Sweet",
            "Fruity"
        ],
        "Aroma": [
            "Floral",
            "Fruity"
        ],
        "Texture": [
            "Bubbly",
            "Refreshing"
        ],
        "Visual_Color": [
            "#FFC0CB",
            "#E4E8EA"
        ],
        "Spice_level": []
    },
    "Societal_Properties": {
        "Dietary_restrictions": [],
        "Nutrition": [
            "Low-Calorie"
        ],
        "Country_Origin": [
            "Italy"
        ],
        "Occasions": [
            "Appetizer",
            "Party"
        ],
        "Cooking_Method": [
            "Not Required"
        ],
        "Course": [
            "Appetizer"
        ]
    },
    "Food_History": {
        "Likes": [],
        "Comments": [],
        "Reviews": [],
        "Amt_bought": [],
        "Promoted": []
    }
}