{
    "name": "enchiladas famosas",
    "Food_Item_UUID": "f4bf456c-9499-4b87-871f-766473323356",
    "User_UUID": "8f90c2ea-b027-4a05-a5ea-969134c8652c",
    "Description": "two cheese enchiladas",
    "Flavor_Profile": {
        "Taste": [
            "Rich",
            "Savory"
        ],
        "Aroma": [
            "Cheesy",
            "Fragrant"
        ],
        "Texture": [
            "Creamy",
            "Tender"
        ],
        "Visual_Color": [
            "#FFC400",
            "#FFFFFF"
        ],
        "Spice_level": [
            "Mild"
        ]
    },
    "Societal_Properties": {
        "Dietary_restrictions": [
            "Dairy"
        ],
        "Nutrition": [
            "High-Calorie"
        ],
        "Country_Origin": [
            "Mexico"
        ],
        "Occasions": [
            "Snack",
            "Lunch",
            "Brunch"
        ],
        "Cooking_Method": [
            "Grilled"
        ],
        "Course": [
            "Appetizer",
            "Main Course"
        ]
    },
    "Food_History": {
        "Likes": [],
        "Comments": [],
        "Reviews": [],
        "Amt_bought": [],
        "Promoted": []
    }
}